Metadata-Version: 2.1
Name: hub-shm
Version: 1.0.0
Summary: Hub Shared Memory
Home-page: https://www.activeloop.ai
Author: activeloop.ai
Author-email: abhinav@activeloop.ai
License: UNKNOWN
Download-URL: https://github.com/activeloopai/hub_shm/archive/refs/tags/1.0.0.tar.gz
Platform: UNKNOWN
License-File: LICENSE
